{
  "totalFiles": 1,
  "successCount": 1,
  "errorCount": 0,
  "processedAt": "2025-11-28T04:24:34.113Z",
  "files": [
    {
      "filename": "csr_program_analyze.docx",
      "fileType": "application/vnd.openxmlformats-officedocument.wordprocessingml.document",
      "extension": "docx",
      "size": 25320,
      "lastModified": "2025-10-09T12:26:33.010Z",
      "extractedAt": "2025-11-28T04:24:34.112Z",
      "data": {
        "type": "unstructured_text",
        "lineCount": 299,
        "content": "CSR Programs Using AI for Women Empowerment\n\n\n\nAI Assistant\n\nCSR Partner(s)\n\nFocus Area\n\nAI Features\n\nYashoda AI\n\nNCW + Future Shift Labs\n\nDigital literacy & safety\n\nConversational agent, local language\n\nAI Kiran\n\nVerix + Govt + CSR donors\n\nWomen in AI careers\n\nMentorship, career agents, badges\n\nAI for All\n\nIntel + Ministry of Edu\n\nAI education for all\n\nLearning modules, certification\n\n\n\nWhat Is Yashoda AI?\n\nYashoda AI is a government-backed AI assistant launched by the National Commission for Women (NCW) in collaboration with Future Shift Labs. It‚Äôs designed to empower women‚Äîespecially in rural and semi-urban India‚Äîby teaching them how to use digital tools safely, understand AI, and protect themselves online.\n\nUnlike typical apps, Yashoda AI is not available for download. Instead, it‚Äôs deployed through community workshops, colleges, police departments, and NGOs. It works like a chatbot that talks to users in simple language and local dialects.\n\n Purpose of Yashoda AI\n\nThe main goals of Yashoda AI are:\n\nüß† Teach women what AI is and how it affects their lives\n\nüîê Help women stay safe online (cybersecurity, privacy)\n\nüì± Build confidence in using mobile phones, apps, and social media\n\nüö® Guide women on how to report cybercrime or digital abuse\n\nüí¨ Promote digital leadership and awareness in communities\n\nHow Yashoda AI Reaches Women\n\nYashoda AI is deployed through organized sessions in partnership with local institutions. Here's how it reaches different groups:\n\n1. Universities and Colleges\n\nWorkshops are held for students and faculty\n\nWomen police officers are invited to participate\n\nSessions include interactive lessons and live demos\n\n2. Police Departments\n\nUsed in cybercrime awareness programs\n\nHelps women understand how to report digital threats\n\nBuilds trust between law enforcement and women\n\n3. Self-Help Groups (SHGs) and ASHA Workers\n\nSessions are conducted in villages and towns\n\nTargets grassroots women leaders and health workers\n\nFocuses on practical safety and digital literacy\n\n4. Community Centers and NGOs\n\nDelivered in low-bandwidth areas using shared devices\n\nSupported by CSR donors and local government bodies\n\nAccessible to women with limited tech exposure\n\n How Yashoda AI Works (Technology)\n\nYashoda AI is a conversational AI assistant‚Äîlike a chatbot that talks to users. It uses:\n\nTechnologies Behind It\n\nNatural Language Processing (NLP) to understand questions\n\nMultilingual support for Tamil, Hindi, and other Indian languages\n\nScenario-based learning to teach through real-life examples\n\nInteractive quizzes to reinforce learning\n\nLightweight deployment for low-internet environments\n\nIt doesn‚Äôt require high-end phones or fast internet. It‚Äôs designed to work in community settings with basic devices.\n\n What Yashoda AI Teaches (Course Levels)\n\nYashoda AI offers structured learning in three levels:\n\nLevel 1: AI Awareness\n\nWhat is AI?\n\nHow does AI affect daily life?\n\nExamples of AI in mobile apps, banking, and social media\n\nLevel 2: Digital Safety & Privacy\n\nHow to set strong passwords\n\nHow to spot scams, fake messages, and phishing\n\nHow to report cybercrime (with links to government portals)\n\nLevel 3: Digital Leadership\n\nHow to become a ‚ÄúDigital Sakhi‚Äù (digital friend/guide)\n\nHow to teach others in your community\n\nHow to use AI tools for education, business, or outreach\n\nEach level includes:\n\nSimple explanations\n\nReal-life scenarios\n\nQuizzes and certifications\n\nLocal language support\n\nImpact of Yashoda AI\n\nYashoda AI has already made a strong impact:\n\n‚úÖ Trained over 2,500 women across India\n\n‚úÖ Reached students, SHG members, ASHA workers, and entrepreneurs\n\n‚úÖ Helped women become confident digital users\n\n‚úÖ Created community leaders who teach others\n\n‚úÖ Supported India‚Äôs mission for women-led digital development\n\n \n\n How the Yashoda AI Initiative Started\n\nInitiated by: National Commission for Women (NCW)\n\nDeveloped by: Future Shift Labs\n\nLaunch Date: May 22, 2025, at Mahatma Jyotiba Phule Rohilkhand University, Bareilly\n\nPurpose of the Initiative\n\nEquip women with AI literacy\n\nPromote digital inclusion\n\nEmpower women in cybersecurity, digital privacy, and safe online practices\n\nAlign with India‚Äôs vision of women-led development and Viksit Bharat\n\nHow Yashoda AI Was Developed\n\nWhile exact development timelines aren‚Äôt publicly disclosed, here‚Äôs a typical breakdown based on similar AI literacy projects:\n\n1. Planning Phase (2‚Äì4 weeks)\n\nDefine goals and target audience (rural and semi-urban women)\n\nIdentify key learning areas: AI basics, cybersecurity, privacy\n\nPartner with universities, police departments, and NGOs\n\n2. Content & Curriculum Design (3‚Äì6 weeks)\n\nCreate multilingual learning modules\n\nDevelop scenario-based lessons and quizzes\n\nAlign with government safety guidelines and digital policies\n\n3. Technical Development (4‚Äì8 weeks)\n\nBuild the conversational AI assistant\n\nIntegrate Natural Language Processing (NLP) for local languages\n\nOptimize for low-bandwidth environments and shared devices\n\n4. Pilot Testing & Deployment (2‚Äì4 weeks)\n\nTest in selected colleges and community centers\n\nTrain facilitators and volunteers\n\nCollect feedback and refine the assistant\n\nSmile Foundation:\n\nWhat Is Smile Foundation?\n\nSmile Foundation is a nonprofit organization in India that works to improve education, healthcare, and livelihood for underprivileged communities. One of its key missions is empowering women, especially in rural and semi-urban areas.\n\nTo scale its impact, Smile Foundation partners with CSR programs from major tech companies like:\n\nInfosys\n\nTCS (Tata Consultancy Services)\n\nWipro\n\nAmerican Express\n\nThese companies support Smile Foundation through CSR funding, technology support, and volunteer mentoring.\n\nGoals of the Program\n\nThe main goals are to:\n\nüß† Teach women how to use digital tools confidently\n\nüíº Help women start small businesses or find jobs\n\nüí∞ Improve financial literacy and independence\n\nüì± Promote safe and smart use of mobile phones and apps\n\nü§ñ Introduce AI tools that make learning and business easier\n\n\n\nWhat Women Learn\n\n1. Digital Literacy\n\nWomen learn:\n\nHow to use smartphones, internet, email, and apps\n\nHow to fill online forms and use government websites\n\nHow to stay safe online and protect their privacy\n\nHow to use AI-powered learning apps that adjust to their level\n\n2. Entrepreneurship Skills\n\nWomen are trained to:\n\nStart small businesses (like tailoring, food stalls, crafts)\n\nUse WhatsApp Business, Instagram, and online marketplaces\n\nCreate digital catalogs and manage orders\n\nUse AI tools to track sales, customer behavior, and marketing\n\n3. Financial Literacy\n\nWomen learn:\n\nHow to use UPI, mobile wallets, and online banking\n\nHow to avoid digital fraud and scams\n\nHow to budget, save, and plan their finances\n\nAI apps help guide them and send alerts for risky transactions\n\n4. STEM Education for Girls\n\nGirls in schools are taught:\n\nBasics of coding and robotics\n\nWhat AI is and how it works\n\nCareer options in science and technology\n\nSupported by Infosys and TCS through scholarships and workshops\n\n5. Career Re-entry Programs\n\nWomen who left jobs due to marriage, motherhood, or other reasons are:\n\nTrained in updated tech skills\n\nMentored by professionals\n\nConnected to job opportunities\n\nAI tools match them to jobs and track their progress\n\n\n\nü§ñ How AI Is Used in These Programs\n\nAI Feature\n\nHow It Helps Women\n\nPersonalized Learning\n\nAdapts lessons to each woman‚Äôs pace and level\n\nChatbots\n\nAnswer questions and guide users step by step\n\nVoice Interfaces\n\nHelp women who struggle with reading or typing\n\nMultilingual Support\n\nTeaches in Tamil, Hindi, and other local languages\n\nBusiness Analytics\n\nHelps women track sales, customer trends, and inventory\n\nFinancial Alerts\n\nWarns about fraud and helps with budgeting\n\nAI turns smartphones into personal tutors, business advisors, and safety guides‚Äîmaking learning accessible and practical.\n\n\n\nüß≠ How AI Finds, Adjusts, and Gives Lessons (Step-by-Step)\n\nStep 1: User Opens the Learning App or Assistant\n\nThe woman uses a mobile app, chatbot, or voice assistant provided during training.\n\nStep 2: AI Asks Simple Questions to Understand the User\n\nExample: ‚ÄúDo you know how to use WhatsApp?‚Äù or ‚ÄúWhat language do you prefer?‚Äù\n\nStep 3: AI Adjusts the Lesson Based on Her Answers\n\nBeginners get basic lessons (e.g., how to open an app)\n\nAdvanced users get business or financial modules\n\nStep 4: AI Gives Lessons in Simple Language\n\nLessons are shown as short videos, voice instructions, or step-by-step guides\n\nStep 5: AI Tracks Progress\n\nRemembers completed lessons, struggles, and preferences\n\nRecommends next steps or repeats topics if needed\n\nStep 6: AI Sends Alerts and Tips\n\nWarns about scams, suggests business tools, and offers financial advice\n\n\n\nü§ù CSR Partners Supporting the Program\n\nCompany\n\nContribution\n\nInfosys\n\nSTEM education, scholarships, career mentoring\n\nTCS\n\n‚ÄúRebegin‚Äù program for career re-entry\n\nWipro\n\nDigital inclusion and tech skilling\n\nAmerican Express\n\nDigital training for women graduates\n\nThese companies support Smile Foundation under India‚Äôs CSR law, which requires them to spend 2% of net profits on social impact.\n\n\n\nüìà Impact So Far\n\n‚úÖ Over 150,000 women trained in digital literacy and entrepreneurship in 2023\n\n‚úÖ Active in 25 states, reaching 1.5 million people annually\n\n‚úÖ Supported micro-business growth and job placements\n\n‚úÖ Improved digital confidence and safety awareness\n\n‚úÖ Created community leaders who teach others\n\n\n\nAI-Based Difference Between Smile Foundation & Yashoda AI\n\nüü© Smile Foundation‚Äôs AI Programs\n\nThese are many small AI tools used in different ways to help women learn, grow businesses, and manage money.\n\n‚úÖ How AI Is Used:\n\nLearning App: AI adjusts lessons based on each woman‚Äôs level (beginner or advanced).\n\nChatbots: Answer questions like ‚ÄúHow do I use UPI?‚Äù or ‚ÄúHow to sell online?‚Äù\n\nVoice Support: Women can speak instead of typing‚Äîgreat for those who can‚Äôt read or write well.\n\nLocal Languages: AI speaks in Tamil, Hindi, etc.\n\nBusiness Tools: AI helps track sales, customers, and gives marketing tips.\n\nFinancial Alerts: AI warns about scams or risky spending.\n\nüéØ Goal:\n\nTo help women become confident with digital tools, start businesses, and manage money.\n\nüü® Yashoda AI\n\nThis is one focused AI assistant‚Äîlike a chatbot teacher‚Äîused in workshops to teach women about AI and digital safety.\n\n‚úÖ How AI Is Used:\n\nChatbot Assistant: Talks to women in simple language.\n\nScenario-Based Learning: Gives examples like ‚ÄúWhat to do if someone sends a fake link?‚Äù\n\nQuizzes: Tests understanding after each topic.\n\nLocal Language Support: Speaks in Tamil, Hindi, etc.\n\nOffline-Friendly: Works in low internet areas during training sessions.\n\nüéØ Goal:\n\nTo teach women how to stay safe online, understand AI, and report cybercrime.\n\n\n\nFeature\n\nSmile Foundation AI\n\nYashoda AI\n\nAI Type\n\nMany small tools\n\nOne chatbot assistant\n\nUsed For\n\nLearning, business, finance\n\nAI awareness and safety\n\nAccess\n\nPublic apps and training\n\nUsed only in workshops\n\nLanguage Support\n\nTamil, Hindi, voice-enabled\n\nTamil, Hindi, simple dialogue\n\nPersonalization\n\nAdapts to user level\n\nFixed lessons and quizzes\n\nGoal\n\nEmpower through tech & business\n\nEmpower through safety & awareness\n\n\n\n\n\n\n\n\n\n\n\nComparison: GenAI for Nonprofit vs Yashoda AI vs Smile Foundation AI\n\nFeature / AI Capability\n\nGenAI System (Custom Virtual Staff)\n\nYashoda AI (Safety Chatbot)\n\nSmile Foundation AI (Learning Toolkit)\n\nAI Role\n\nFull virtual team member\n\nChatbot teacher\n\nLearning assistant\n\nScope of Tasks\n\nEnd-to-end: grant search, application, reporting, outreach\n\nFocused: teach AI safety and digital literacy\n\nModular: teach digital skills, business, finance\n\nAutonomy Level\n\nHigh ‚Äî AI acts independently with minimal human input\n\nLow ‚Äî used only in workshops\n\nMedium ‚Äî supports learning, needs human review\n\nAI Behavior\n\nProactive, strategic, context-aware\n\nReactive, scenario-based\n\nAdaptive, lesson-based\n\nPersonalization\n\nTailors proposals, reports, and outreach per funder\n\nFixed content per session\n\nAdapts lessons to user level\n\nData Integration\n\nPulls from website, surveys, media folders\n\nNo external data integration\n\nUses internal learning modules\n\nImpact Analysis\n\nAI analyzes behavioral change (confidence, resilience)\n\nNo impact tracking\n\nTracks basic metrics (skills, attendance)\n\nDocument Handling\n\nAuto-assembles applications with attachments\n\nNo document handling\n\nManual uploads for training\n\nDonor Engagement\n\nAI sends emails, books meetings, tracks responses\n\nNo donor engagement\n\nDonor reports are manually prepared\n\nGrant Discovery\n\nAI crawls web, filters by mission, updates live database\n\nNo grant discovery\n\nGrant search is manual\n\nReporting & Dashboards\n\nAI creates visual reports, summaries, case studies\n\nNo reporting\n\nBasic reporting with human input\n\nScalability\n\nManages multiple pipelines simultaneously\n\nUsed in limited sessions\n\nScales across training centers\n\n\n\n\n\n",
        "detectedPatterns": [
          "key-value",
          "key-value",
          "key-value",
          "key-value",
          "key-value",
          "key-value",
          "key-value",
          "key-value",
          "key-value",
          "key-value",
          "key-value",
          "key-value",
          "key-value",
          "key-value",
          "key-value",
          "key-value",
          "key-value",
          "key-value",
          "key-value",
          "key-value",
          "key-value",
          "key-value",
          "key-value",
          "key-value",
          "key-value",
          "key-value",
          "key-value",
          "key-value",
          "key-value"
        ],
        "keyValuePairs": {
          "Level 1": "AI Awareness",
          "Level 2": "Digital Safety & Privacy",
          "Level 3": "Digital Leadership",
          "Initiated by": "National Commission for Women (NCW)",
          "Developed by": "Future Shift Labs",
          "Launch Date": "May 22, 2025, at Mahatma Jyotiba Phule Rohilkhand University, Bareilly",
          "Identify key learning areas": "AI basics, cybersecurity, privacy",
          "Step 1": "User Opens the Learning App or Assistant",
          "Step 2": "AI Asks Simple Questions to Understand the User",
          "Example": "‚ÄúDo you know how to use WhatsApp?‚Äù or ‚ÄúWhat language do you prefer?‚Äù",
          "Step 3": "AI Adjusts the Lesson Based on Her Answers",
          "Step 4": "AI Gives Lessons in Simple Language",
          "Step 5": "AI Tracks Progress",
          "Step 6": "AI Sends Alerts and Tips",
          "Learning App": "AI adjusts lessons based on each woman‚Äôs level (beginner or advanced).",
          "Chatbots": "Answer questions like ‚ÄúHow do I use UPI?‚Äù or ‚ÄúHow to sell online?‚Äù",
          "Voice Support": "Women can speak instead of typing‚Äîgreat for those who can‚Äôt read or write well.",
          "Local Languages": "AI speaks in Tamil, Hindi, etc.",
          "Business Tools": "AI helps track sales, customers, and gives marketing tips.",
          "Financial Alerts": "AI warns about scams or risky spending.",
          "Chatbot Assistant": "Talks to women in simple language.",
          "Scenario-Based Learning": "Gives examples like ‚ÄúWhat to do if someone sends a fake link?‚Äù",
          "Quizzes": "Tests understanding after each topic.",
          "Local Language Support": "Speaks in Tamil, Hindi, etc.",
          "Offline-Friendly": "Works in low internet areas during training sessions.",
          "Comparison": "GenAI for Nonprofit vs Yashoda AI vs Smile Foundation AI",
          "End-to-end": "grant search, application, reporting, outreach",
          "Focused": "teach AI safety and digital literacy",
          "Modular": "teach digital skills, business, finance"
        }
      }
    }
  ]
}